LICENSE.txt
MANIFEST.in
README.md
setup.cfg
setup.py
requirements/requirements.txt
vatis/asr/amqp/queue/__init__.py
vatis/asr/amqp/queue/connection.py
vatis/asr/amqp/queue/constants.py
vatis/asr/amqp/queue/consumer.py
vatis/asr/amqp/queue/environment.py
vatis/asr/amqp/queue/exceptions.py
vatis/asr/amqp/queue/headers.py
vatis/asr/amqp/queue/listener.py
vatis/asr/amqp/queue/model.py
vatis/asr/amqp/queue/parse.py
vatis/asr/amqp/queue/publisher.py
vatis/asr/amqp/queue/routing.py
vatis/asr/amqp/queue/rpc.py
vatis_asr_amqp.egg-info/PKG-INFO
vatis_asr_amqp.egg-info/SOURCES.txt
vatis_asr_amqp.egg-info/dependency_links.txt
vatis_asr_amqp.egg-info/namespace_packages.txt
vatis_asr_amqp.egg-info/not-zip-safe
vatis_asr_amqp.egg-info/requires.txt
vatis_asr_amqp.egg-info/top_level.txt