Metadata-Version: 2.1
Name: vatis-asr-amqp
Version: 1.2.0
Summary: AMQP client implementation over Pika library
Home-page: https://gitlab.com/vatistech/asr-amqp
Maintainer: VATIS TECH
Maintainer-email: support@vatis.tech
License: UNKNOWN
Download-URL: https://gitlab.com/vatistech/asr-amqp/-/archive/1.2.0/asr_amqp-1.2.0.zip
Platform: UNKNOWN
Classifier: Development Status :: 4 - Beta
Classifier: Intended Audience :: Developers
Classifier: License :: OSI Approved :: Apache Software License
Classifier: Programming Language :: Python
Classifier: Programming Language :: Python :: 3
Classifier: Programming Language :: Python :: 3.6
Classifier: Programming Language :: Python :: 3.7
Classifier: Programming Language :: Python :: 3.8
Classifier: Programming Language :: Python :: 3.9
Classifier: Operating System :: OS Independent
Classifier: Topic :: Software Development :: Build Tools
Classifier: Topic :: Internet
Requires-Python: >=3.6
License-File: LICENSE.txt
